bdl/__init__.py
bdl/core.py
bdl/version.py
zen_bdl-0.2.2.dist-info/LICENSE
zen_bdl-0.2.2.dist-info/METADATA
zen_bdl-0.2.2.dist-info/WHEEL
zen_bdl-0.2.2.dist-info/entry_points.txt
zen_bdl-0.2.2.dist-info/top_level.txt
zen_bdl-0.2.2.dist-info/RECORD
